vertex/__init__.py
vertex/__main__.py
vertex/minicli.py
vertex/templates.py
vertexengine_cli-1.2rc1.dist-info/licenses/LICENSE
vertexengine_cli-1.2rc1.dist-info/METADATA
vertexengine_cli-1.2rc1.dist-info/WHEEL
vertexengine_cli-1.2rc1.dist-info/entry_points.txt
vertexengine_cli-1.2rc1.dist-info/top_level.txt
vertexengine_cli-1.2rc1.dist-info/RECORD
