Metadata-Version: 2.4
Name: VertexEngine-CLI
Version: 1.2rc1
Summary: An Offical CLI library for VertexEngine.
Author-email: Tyrel Miguel <annbasilan0828@gmail.com>
License: MIT
Project-URL: Documentation, https://vertexenginedocs.netlify.app/
Project-URL: Homepage, https://github.com/TyrelGomez/VertexEngine-CLI-Code
Requires-Python: >=3.10
License-File: LICENSE
Requires-Dist: pygame>=2.0
Requires-Dist: PyQt6>=6.7
Requires-Dist: pyinstaller>=6.5.0
Requires-Dist: VertexEngine>=1.0.1
Dynamic: license-file
